oeis/__init__.py
oeis/abundant.py
oeis/arithmetic.py
oeis/buttered_croissant.py
oeis/carmichael.py
oeis/catalan.py
oeis/centered_polygonal.py
oeis/composite.py
oeis/deficient.py
oeis/eratosthenes.py
oeis/factorial.py
oeis/fermat.py
oeis/fibonacci.py
oeis/hilbert.py
oeis/icosahedral.py
oeis/jacobsthal.py
oeis/juggler.py
oeis/kynea.py
oeis/lazy_caterer.py
oeis/leonardo.py
oeis/loeschian.py
oeis/lucas.py
oeis/mersenne.py
oeis/oblong.py
oeis/padovan.py
oeis/pell.py
oeis/perfect.py
oeis/period2.py
oeis/perrin.py
oeis/polite.py
oeis/polygonal.py
oeis/py.typed
oeis/pyramidal.py
oeis/quasiperfect.py
oeis/recaman.py
oeis/registry/__init__.py
oeis/rough.py
oeis/semiperfect.py
oeis/smooth.py
oeis/sorting.py
oeis/squarefree.py
oeis/superperfect.py
oeis/sylvester.py
oeis/totient.py
oeis/tribonacci.py
oeis/unusual.py
oeis/utils/__init__.py
oeis/vauban.py
oeis/weird.py
oeis/woodall.py
oeis_seq-0.1.9.dist-info/LICENSE
oeis_seq-0.1.9.dist-info/WHEEL
oeis_seq-0.1.9.dist-info/METADATA
oeis_seq-0.1.9.dist-info/RECORD
